README.txt
setup.cfg
setup.py
GalleryRemote.egg-info/PKG-INFO
GalleryRemote.egg-info/SOURCES.txt
GalleryRemote.egg-info/dependency_links.txt
GalleryRemote.egg-info/not-zip-safe
GalleryRemote.egg-info/top_level.txt
galleryremote/__init__.py
galleryremote/gallery.py
galleryremote/multipart.py