Metadata-Version: 1.0
Name: GalleryRemote
Version: 0.7dev
Summary: Implementation of the Gallery Remote protocol in Python.
Home-page: http://pietrobattiston.it/galleryremote
Author: Pietro Battiston
Author-email: me@pietrobattiston.it
License: GPL
Keywords: gallery gallery2 remote images pictures albums
Platform: UNKNOWN
Classifier: Development Status :: 4 - Beta
Classifier: Intended Audience :: Developers
Classifier: License :: OSI Approved :: GNU General Public License (GPL)
Classifier: Topic :: Multimedia :: Graphics
